setup.py
funniest22222.egg-info/PKG-INFO
funniest22222.egg-info/SOURCES.txt
funniest22222.egg-info/dependency_links.txt
funniest22222.egg-info/not-zip-safe
funniest22222.egg-info/top_level.txt
funniest2223/__init__.py